sqlitelib/__init__.py
sqlitelib/database/__init__.py
sqlitelib/database/base.py
sqlitelib/database/common.py
sqlitelib/database/connection.py
sqlitelib/database/db.py
sqlitelib/database/session.py
sqlitelib/sql/__init__.py
sqlitelib/sql/dml.py
sqlitelib/sql/pragma.py
sqlitelib/table/__init__.py
sqlitelib/table/column.py
sqlitelib/table/column_enum.py
sqlitelib/table/model.py
sqlitelib/utils/__init__.py
sqlitelib/utils/common.py
sqlitelib/utils/encoding.py
sqlitelib-1.0.4.dist-info/LICENSE
sqlitelib-1.0.4.dist-info/METADATA
sqlitelib-1.0.4.dist-info/WHEEL
sqlitelib-1.0.4.dist-info/top_level.txt
sqlitelib-1.0.4.dist-info/RECORD
