Metadata-Version: 2.2
Name: sqlitelib
Version: 1.0.4
Summary: A sqlite lib that encapsulate common sqlite operations
Home-page: https://github.com/kejun91/sqlitelib
Author: Jun Ke
Author-email: kejun91@gmail.com
Classifier: Programming Language :: Python :: 3
Classifier: License :: OSI Approved :: MIT License
Classifier: Operating System :: OS Independent
Requires-Python: >=3.6
License-File: LICENSE
Dynamic: author
Dynamic: author-email
Dynamic: classifier
Dynamic: description
Dynamic: description-content-type
Dynamic: home-page
Dynamic: requires-python
Dynamic: summary
